LICENSE
MANIFEST.in
README.md
pyproject.toml
requirements.txt
setup.py
bitvector/.git
bitvector/.gitignore
bitvector/LICENSE
bitvector/Makefile
bitvector/README.md
bitvector/bitvector.c
bitvector/bitvector.h
bitvector/tests.c
pasp/__init__.py
pasp/app.py
pasp/approx.c
pasp/capprox.c
pasp/capprox.h
pasp/carray.c
pasp/carray.h
pasp/caseo.c
pasp/caseo.h
pasp/ccounter.c
pasp/ccounter.h
pasp/cdata.c
pasp/cdata.h
pasp/cexact.c
pasp/cexact.h
pasp/cground.c
pasp/cground.h
pasp/cinf.c
pasp/cinf.h
pasp/clearn.c
pasp/clearn.h
pasp/cmap.cc
pasp/cmap.hh
pasp/cmodels.c
pasp/cmodels.h
pasp/coptimize.c
pasp/coptimize.h
pasp/cprogram.c
pasp/cprogram.h
pasp/csample.c
pasp/csample.h
pasp/cstorage.c
pasp/cstorage.h
pasp/cthread.c
pasp/cthread.h
pasp/ctree.c
pasp/ctree.h
pasp/cutils.c
pasp/cutils.h
pasp/exact.c
pasp/grammar.lark
pasp/grammar.py
pasp/ground.c
pasp/learn.c
pasp/program.py
pasp/sample.c
pasp/wlearn.py
pasp_plp.egg-info/PKG-INFO
pasp_plp.egg-info/SOURCES.txt
pasp_plp.egg-info/dependency_links.txt
pasp_plp.egg-info/entry_points.txt
pasp_plp.egg-info/requires.txt
pasp_plp.egg-info/top_level.txt
progressbar/LICENSE
progressbar/progressbar.c
progressbar/progressbar.h
progressbar/statusbar.c
progressbar/statusbar.h
tests/__init__.py
tests/counting.py
tests/examples.py
tests/learning.py
tests/sampling.py
tests/single.py
tests/utils.py
thpool/LICENSE
thpool/thpool.c
thpool/thpool.h