Metadata-Version: 2.1
Name: pasp-plp
Version: 0.0.5.post1
Summary: Probabilistic Answer Set Programming
Author-email: Renato Lui Geh <renatogeh@gmail.com>
License: MIT
Project-URL: Repository, https://github.com/RenatoGeh/pasp
Project-URL: Issues, https://github.com/RenatoGeh/pasp/issues
Classifier: Programming Language :: Python :: 3
Classifier: License :: OSI Approved :: MIT License
Classifier: Operating System :: POSIX :: Linux
Classifier: Development Status :: 3 - Alpha
Classifier: Environment :: Console
Classifier: Intended Audience :: Science/Research
Classifier: Topic :: Scientific/Engineering :: Artificial Intelligence
Requires-Python: >=3.10
License-File: LICENSE
Requires-Dist: clingo>=5.6.2
Requires-Dist: lark>=1.1.5
Requires-Dist: numpy>=1.23.5
Requires-Dist: pandas>=1.5.3
Provides-Extra: torch
Requires-Dist: torch>=1.13.1; extra == "torch"
